cirillo.py
cirillo-1.0.0.dist-info/METADATA
cirillo-1.0.0.dist-info/WHEEL
cirillo-1.0.0.dist-info/entry_points.txt
cirillo-1.0.0.dist-info/licenses/LICENSE.md
cirillo-1.0.0.dist-info/RECORD
