Metadata-Version: 2.1
Name: cirillo
Version: 1.0.0
Summary: Command line Pomodoro timer
Project-URL: Homepage, https://github.com/nerandell/cirillo
Project-URL: Bug Tracker, https://github.com/nerandell/cirillo/issues
Author-email: Ankit Chandawala <ankitchandawala@gmail.com>
License-File: LICENSE.md
Classifier: License :: OSI Approved :: MIT License
Classifier: Operating System :: OS Independent
Classifier: Programming Language :: Python :: 3
Requires-Python: >=3.7
Requires-Dist: click
Requires-Dist: colorama
Requires-Dist: plyer
Requires-Dist: tqdm
